main.py
tasks/__init__.py
tasks/data_analysis.py
tasks/dummy.py
spryfox_assessment_tc-0.1.1.dist-info/METADATA
spryfox_assessment_tc-0.1.1.dist-info/WHEEL
spryfox_assessment_tc-0.1.1.dist-info/RECORD
