Metadata-Version: 2.1
Name: spryfox-assessment-tc
Version: 0.1.1
Summary: 
Author: Tiziano Cocciò
Author-email: tiziano.coccio@gmail.com
Requires-Python: >=3.10,<4.0
Classifier: Programming Language :: Python :: 3
Classifier: Programming Language :: Python :: 3.10
Classifier: Programming Language :: Python :: 3.11
Requires-Dist: matplotlib (==3.7.0)
Requires-Dist: pandas (==1.5.3)
